query_extract.py
Query_Extract-1.0.5.dist-info/LICENSE
Query_Extract-1.0.5.dist-info/METADATA
Query_Extract-1.0.5.dist-info/WHEEL
Query_Extract-1.0.5.dist-info/top_level.txt
Query_Extract-1.0.5.dist-info/RECORD
